<?xml version="1.0" encoding="UTF-8"?>
<!-- © 2016 Carlos Dauden <carlos.dauden@tecnativa.com>
     License AGPL-3.0 or later (http://www.gnu.org/licenses/agpl-3). -->
<openerp>
<data>

<!-- Product Product -->
<record id="product_normal_website_pack_form_view" model="ir.ui.view">
    <field name="name">product.product.website.pack.form</field>
    <field name="model">product.product</field>
    <field name="inherit_id" ref="product.product_normal_form_view"/>
    <field name="arch" type="xml">
        <xpath expr="//page[@string='Sales']" position="after">
            <page name="website_packs" string="Website Packs">
                <group>
                    <field name="website_pack_ids" readonly="1" widget="many2many_tags"/>
                </group>
            </page>
        </xpath>
    </field>
</record>

<!-- Product Public Categories -->
<record id="product_public_category_pack_form_view" model="ir.ui.view">
    <field name="name">product.public.category.pack.form</field>
    <field name="model">product.public.category</field>
    <field name="inherit_id" ref="website_sale.product_public_category_form_view"/>
    <field name="arch" type="xml">
        <xpath expr="//field[@name='name']/../.." position="attributes">
            <attribute name="class"></attribute>
        </xpath>
        <xpath expr="//field[@name='name']/../.." position="after">
            <group string="Website Packs">
                <field name="website_pack_ids" nolabel="1"
                       context="{'default_public_categ_ids': [active_id]}">
                    <tree string="Packs">
                        <field name="sequence" widget="handle"/>
                        <field name="block"/>
                        <field name="line_ids" widget="one2many_tags">
                        </field>
                    </tree>
                    <form string="Pack">
                        <sheet>
                            <group>
                                <field name="block"/>
                            </group>
                            <field name="line_ids">
                                <tree string="Products" editable="bottom">
                                    <field name="sequence" widget="handle"/>
                                    <field name="product_id"/>
                                    <field name="default_checked"/>
                                </tree>
                            </field>
                        </sheet>
                    </form>
                </field>
            </group>
        </xpath>
    </field>
</record>

</data>
</openerp>
